template_models/__init__.py
template_models/llm_template_model.py
template_models/py.typed
template_models/template_model.py
template_models-0.2.1.dist-info/METADATA
template_models-0.2.1.dist-info/WHEEL
template_models-0.2.1.dist-info/RECORD
